{
	"RunDate": "2023-06-08T14:53:59.273479-07:00",
	"NRDiagVersion": "",
	"Configuration": {
		"Verbose": false,
		"Quiet": false,
		"VeryQuiet": false,
		"YesToAll": false,
		"ShowOverrideHelp": false,
		"AutoAttach": false,
		"ProxySpecified": false,
		"SkipVersionCheck": false,
		"Tasks": "",
		"ConfigFile": "",
		"Override": "",
		"OutputPath": "",
		"Filter": "",
		"BrowserURL": "",
		"Suites": "",
		"APIKey": "",
		"Include": "",
		"Region": ""
	},
	"Results": [
		{
			"Identifier": {
				"Category": "Base",
				"Subcategory": "Log",
				"Name": "Collect"
			},
			"Override": false,
			"Result": {
				"Status": "Success",
				"Summary": "Streamed data",
				"URL": "",
				"FilesToCopy": [
					{
						"Path": "data.txt",
						"Name": "Base/Log/data.txt",
						"Streamed": true
					}
				],
				"Payload": null
			}
		}
	]
}